{
  "updatedAt": "2026-04-22T18:17:39.360Z",
  "createdAt": "2026-04-22T17:43:30.792Z",
  "id": "8DlUtG72SAqx1DYm",
  "name": "get historico chatwoot",
  "active": false,
  "isArchived": false,
  "nodes": [
    {
      "parameters": {
        "operation": "getAll",
        "tableId": "renovacao_anuncios",
        "returnAll": true
      },
      "id": "7d93d576-da99-49e9-b842-867a07fbffa5",
      "name": "1. Puxar Telefones (Supabase)",
      "type": "n8n-nodes-base.supabase",
      "typeVersion": 1,
      "position": [
        -192,
        -128
      ],
      "credentials": {
        "supabaseApi": {
          "id": "qF5T2ej3TiWXL4jk",
          "name": "Agronegociar - Supabase"
        }
      }
    },
    {
      "parameters": {
        "options": {}
      },
      "id": "1fe7d14e-dddb-4ffd-b125-fe328499c954",
      "name": "2. Loop de Telefones",
      "type": "n8n-nodes-base.splitInBatches",
      "typeVersion": 3,
      "position": [
        32,
        -128
      ]
    },
    {
      "parameters": {
        "url": "https://chat.miabuilder.com/api/v1/accounts/166/contacts/search",
        "sendQuery": true,
        "queryParameters": {
          "parameters": [
            {
              "name": "q",
              "value": "=5511999373076"
            }
          ]
        },
        "sendHeaders": "***REMOVIDO***",
        "headerParameters": {
          "parameters": [
            {
              "name": "api_access_token",
              "value": "TCo9RFKQb3Mg5N8X7HkTSaW3"
            }
          ]
        },
        "options": {}
      },
      "id": "46a5258d-6ad5-455f-9a86-b29894cda37a",
      "name": "3. GET Contato",
      "type": "n8n-nodes-base.httpRequest",
      "typeVersion": 4.2,
      "position": [
        256,
        -128
      ],
      "onError": "continueRegularOutput"
    },
    {
      "parameters": {
        "url": "=https://chat.miabuilder.com/api/v1/accounts/166/contacts/{{ $json.payload[0].id }}/conversations",
        "sendHeaders": "***REMOVIDO***",
        "headerParameters": {
          "parameters": [
            {
              "name": "api_access_token",
              "value": "TCo9RFKQb3Mg5N8X7HkTSaW3"
            }
          ]
        },
        "options": {}
      },
      "id": "7059570a-37ee-4b39-8837-72028e8bb923",
      "name": "4. GET Conversas",
      "type": "n8n-nodes-base.httpRequest",
      "typeVersion": 4.2,
      "position": [
        480,
        -128
      ],
      "onError": "continueRegularOutput"
    },
    {
      "parameters": {
        "url": "=https://chat.miabuilder.com/api/v1/accounts/166/conversations/{{ $json.payload[0].id }}/messages",
        "sendHeaders": "***REMOVIDO***",
        "headerParameters": {
          "parameters": [
            {
              "name": "api_access_token",
              "value": "TCo9RFKQb3Mg5N8X7HkTSaW3"
            }
          ]
        },
        "options": {}
      },
      "id": "bd2f5894-9953-4b23-b2ef-868dcba7608f",
      "name": "5. GET Mensagens",
      "type": "n8n-nodes-base.httpRequest",
      "typeVersion": 4.2,
      "position": [
        688,
        -128
      ],
      "onError": "continueRegularOutput"
    },
    {
      "parameters": {
        "fieldToSplitOut": "payload",
        "options": {}
      },
      "id": "0f903004-cf96-48e1-890f-d69f69d8a254",
      "name": "6. Separar Mensagens",
      "type": "n8n-nodes-base.splitOut",
      "typeVersion": 1,
      "position": [
        912,
        -128
      ]
    },
    {
      "parameters": {
        "tableId": "chatwoot_messages_log",
        "fieldsUi": {
          "fieldValues": [
            {
              "fieldId": "message_id",
              "fieldValue": "={{ $json.id.toString() }}"
            },
            {
              "fieldId": "conversation_id",
              "fieldValue": "={{ $json.conversation_id.toString() }}"
            },
            {
              "fieldId": "sender_type",
              "fieldValue": "={{ $json.message_type === 1 ? 'outgoing' : 'incoming' }}"
            },
            {
              "fieldId": "sender_name",
              "fieldValue": "={{ $json.sender.name }}"
            },
            {
              "fieldId": "content",
              "fieldValue": "={{ $json.content }}"
            },
            {
              "fieldId": "content_type",
              "fieldValue": "={{ $json.content_type }}"
            },
            {
              "fieldId": "created_at",
              "fieldValue": "={{ DateTime.fromSeconds($json.created_at).toISO() }}"
            },
            {
              "fieldId": "telefone",
              "fieldValue": "={{ $node[\"2. Loop de Telefones\"].json.telefone }}"
            },
            {
              "fieldId": "nome_app",
              "fieldValue": "Chatwoot_Log"
            }
          ]
        }
      },
      "id": "da4b222d-5745-4032-b8a8-a1370a85d476",
      "name": "7. Salvar no Supabase (UPSERT)",
      "type": "n8n-nodes-base.supabase",
      "typeVersion": 1,
      "position": [
        1136,
        -128
      ],
      "credentials": {
        "supabaseApi": {
          "id": "qF5T2ej3TiWXL4jk",
          "name": "Agronegociar - Supabase"
        }
      },
      "notes": "Mude para a operação UPSERT e adicione os outros campos"
    },
    {
      "parameters": {
        "amount": 1
      },
      "id": "56a75f10-bd41-4d26-80dd-2c88eaabb2a0",
      "name": "8. Pausa de Segurança",
      "type": "n8n-nodes-base.wait",
      "typeVersion": 1.1,
      "position": [
        1360,
        -128
      ],
      "webhookId": "6ae3518f-53eb-4834-bb75-f4852d0b9731"
    },
    {
      "parameters": {},
      "type": "n8n-nodes-base.manualTrigger",
      "typeVersion": 1,
      "position": [
        -400,
        -128
      ],
      "id": "57704fcd-dbe9-435d-a6e3-be8546d24afd",
      "name": "When clicking ‘Execute workflow’"
    }
  ],
  "connections": {
    "1. Puxar Telefones (Supabase)": {
      "main": [
        [
          {
            "node": "2. Loop de Telefones",
            "type": "main",
            "index": 0
          }
        ]
      ]
    },
    "2. Loop de Telefones": {
      "main": [
        [],
        [
          {
            "node": "3. GET Contato",
            "type": "main",
            "index": 0
          }
        ]
      ]
    },
    "3. GET Contato": {
      "main": [
        [
          {
            "node": "4. GET Conversas",
            "type": "main",
            "index": 0
          }
        ]
      ]
    },
    "4. GET Conversas": {
      "main": [
        [
          {
            "node": "5. GET Mensagens",
            "type": "main",
            "index": 0
          }
        ]
      ]
    },
    "5. GET Mensagens": {
      "main": [
        [
          {
            "node": "6. Separar Mensagens",
            "type": "main",
            "index": 0
          }
        ]
      ]
    },
    "6. Separar Mensagens": {
      "main": [
        [
          {
            "node": "7. Salvar no Supabase (UPSERT)",
            "type": "main",
            "index": 0
          }
        ]
      ]
    },
    "7. Salvar no Supabase (UPSERT)": {
      "main": [
        [
          {
            "node": "8. Pausa de Segurança",
            "type": "main",
            "index": 0
          }
        ]
      ]
    },
    "8. Pausa de Segurança": {
      "main": [
        [
          {
            "node": "2. Loop de Telefones",
            "type": "main",
            "index": 0
          }
        ]
      ]
    },
    "When clicking ‘Execute workflow’": {
      "main": [
        [
          {
            "node": "1. Puxar Telefones (Supabase)",
            "type": "main",
            "index": 0
          }
        ]
      ]
    }
  },
  "settings": {
    "executionOrder": "v1"
  },
  "staticData": null,
  "meta": {
    "templateCredsSetupCompleted": true
  },
  "versionId": "7866750c-b2d4-485e-ab10-db04ef23d759",
  "activeVersionId": null,
  "triggerCount": 0,
  "shared": [
    {
      "updatedAt": "2026-04-22T17:43:30.792Z",
      "createdAt": "2026-04-22T17:43:30.792Z",
      "role": "workflow:owner",
      "workflowId": "8DlUtG72SAqx1DYm",
      "projectId": "nRxOu1L1N41Jyveq"
    }
  ],
  "activeVersion": null,
  "tags": []
}